README.md
setup.py
pyxiaolu/__init__.py
pyxiaolu/pyxiaolu.py
pyxiaolu.egg-info/PKG-INFO
pyxiaolu.egg-info/SOURCES.txt
pyxiaolu.egg-info/dependency_links.txt
pyxiaolu.egg-info/requires.txt
pyxiaolu.egg-info/top_level.txt