Metadata-Version: 2.1
Name: pyxiaolu
Version: 0.1.2
Summary: python库以在小陆同学上执行代码 | python library to execute code on 'xiaolu'
Home-page: https://github.com/krishuang2008/pyxiaolu
Author: krishuang
Author-email: huangzikun2008@hotmail.com
License: UNKNOWN
Platform: UNKNOWN
Classifier: Programming Language :: Python :: 3
Classifier: License :: OSI Approved :: MIT License
Classifier: Operating System :: OS Independent
Requires-Python: >=3.5
